zpenv/__init__.py
zpenv/__main__.py
zpenv/zpenv.py
zpenv-1.3.1.dist-info/LICENSE
zpenv-1.3.1.dist-info/METADATA
zpenv-1.3.1.dist-info/WHEEL
zpenv-1.3.1.dist-info/entry_points.txt
zpenv-1.3.1.dist-info/top_level.txt
zpenv-1.3.1.dist-info/RECORD
