Metadata-Version: 2.1
Name: zpenv
Version: 1.3.1
Summary: Gestionnaire d'environnement virtuel
Home-page: https://github.com/ZephyrOff/py-zpenv
Author: 
License: MIT License
Project-URL: Documentation, https://github.com/ZephyrOff/py-zpenv
Keywords: venv virtualenv terminal zephyroff
Platform: ALL
Classifier: Development Status :: 5 - Production/Stable
Classifier: Environment :: Console
Classifier: License :: OSI Approved :: MIT License
Classifier: Programming Language :: Python :: 3
License-File: LICENSE
Requires-Dist: zpp-args
Requires-Dist: zpp-config
Requires-Dist: psutil
